CONTRIBUTORS.txt
LICENSE
MANIFEST.in
README.md
setup.py
django_cachedpaginator/__init__.py
django_cachedpaginator/admin.py
django_cachedpaginator/helpers.py
django_cachedpaginator/settings.py
django_cachedpaginator/tests.py
django_cachedpaginator/urls.py
django_cachedpaginator/utils.py
django_cachedpaginator/views.py
django_cachedpaginator.egg-info/PKG-INFO
django_cachedpaginator.egg-info/SOURCES.txt
django_cachedpaginator.egg-info/dependency_links.txt
django_cachedpaginator.egg-info/not-zip-safe
django_cachedpaginator.egg-info/top_level.txt
django_cachedpaginator/templates/django_cachedpaginator/paginator_template.html
django_cachedpaginator/templatetags/__init__.py
django_cachedpaginator/templatetags/cached_paginator.py