Metadata-Version: 1.1
Name: django-cachedpaginator
Version: 0.0.5
Summary: Paginator that caches pages automatically.
Home-page: http://github.com/arsham/django-cachedpaginator
Author: Arsham Shirvani
Author-email: arshamshirvani@gmail.com
License: BSD
Keywords: paginator,django,cache
Platform: OS Independen
Classifier: Programming Language :: Python :: 3
Classifier: Programming Language :: Python :: 3.2
Classifier: Programming Language :: Python :: 3.3
Classifier: Programming Language :: Python :: 3.4
Classifier: Topic :: Software Development :: Libraries
Classifier: Intended Audience :: Developers
Classifier: License :: OSI Approved :: BSD License
Classifier: Operating System :: OS Independent
Classifier: Framework :: Django
Classifier: Environment :: Web Environment
